{
  "project_info": {
    "project_number": "711171729873",
    "firebase_url": "https://projectakhir-43226-default-rtdb.asia-southeast1.firebasedatabase.app",
    "project_id": "projectakhir-43226",
    "storage_bucket": "projectakhir-43226.appspot.com"
  },
  "client": [
    {
      "client_info": {
        "mobilesdk_app_id": "1:711171729873:android:5068debd2e43301382d8f0",
        "android_client_info": {
          "package_name": "com.example.flutter_application_1"
        }
      },
      "oauth_client": [
        {
          "client_id": "711171729873-nih2tonlfoo4jirjgh4ps8chp1f665ct.apps.googleusercontent.com",
          "client_type": 1,
          "android_info": {
            "package_name": "com.example.flutter_application_1",
            "certificate_hash": "28ac31000cab52c23cf758618572db8ea8f5c0c7"
          }
        },
        {
          "client_id": "711171729873-39auj1s6o9ugio3maejsgvu67gn707uc.apps.googleusercontent.com",
          "client_type": 3
        }
      ],
      "api_key": [
        {
          "current_key": "AIzaSyAH9MM1MILBwScGK4QL6KNr-OC_Lo-oPbk"
        }
      ],
      "services": {
        "appinvite_service": {
          "other_platform_oauth_client": [
            {
              "client_id": "711171729873-39auj1s6o9ugio3maejsgvu67gn707uc.apps.googleusercontent.com",
              "client_type": 3
            },
            {
              "client_id": "711171729873-qhah2ajc09dnh5hd7fgbparhta4k7g84.apps.googleusercontent.com",
              "client_type": 2,
              "ios_info": {
                "bundle_id": "com.example.flutterApplication1"
              }
            }
          ]
        }
      }
    }
  ],
  "configuration_version": "1"
}